{
    "annotations": {
      "list": [
        {
          "builtIn": 1,
          "datasource": {
            "type": "grafana",
            "uid": "-- Grafana --"
          },
          "enable": true,
          "hide": true,
          "iconColor": "rgba(0, 211, 255, 1)",
          "name": "Annotations & Alerts",
          "target": {
            "limit": 100,
            "matchAny": false,
            "tags": [],
            "type": "dashboard"
          },
          "type": "dashboard"
        }
      ]
    },
    "editable": true,
    "fiscalYearStartMonth": 0,
    "graphTooltip": 0,
    "id": 58,
    "links": [],
    "liveNow": false,
    "panels": [
      {
        "datasource": {
          "type": "prometheus",
          "uid": "ci-prod-aks-weu-mac"
        },
        "fieldConfig": {
          "defaults": {
            "color": {
              "mode": "palette-classic"
            },
            "custom": {
              "axisLabel": "",
              "axisPlacement": "auto",
              "barAlignment": 0,
              "drawStyle": "line",
              "fillOpacity": 0,
              "gradientMode": "none",
              "hideFrom": {
                "legend": false,
                "tooltip": false,
                "viz": false
              },
              "lineInterpolation": "linear",
              "lineWidth": 1,
              "pointSize": 5,
              "scaleDistribution": {
                "type": "linear"
              },
              "showPoints": "auto",
              "spanNulls": false,
              "stacking": {
                "group": "A",
                "mode": "none"
              },
              "thresholdsStyle": {
                "mode": "off"
              }
            },
            "mappings": [],
            "thresholds": {
              "mode": "absolute",
              "steps": [
                {
                  "color": "green",
                  "value": null
                },
                {
                  "color": "red",
                  "value": 80
                }
              ]
            }
          },
          "overrides": []
        },
        "gridPos": {
          "h": 8,
          "w": 12,
          "x": 0,
          "y": 0
        },
        "id": 6,
        "options": {
          "legend": {
            "calcs": [],
            "displayMode": "list",
            "placement": "bottom"
          },
          "tooltip": {
            "mode": "single",
            "sort": "none"
          }
        },
        "targets": [
          {
            "datasource": {
              "type": "prometheus",
              "uid": "ci-prod-aks-weu-mac"
            },
            "expr": "(sum ( node_namespace_pod_container:container_cpu_usage_seconds_total:sum_irate{cluster=\"ci-prod-aks-mac-weu\", namespace=\"kube-system\", container!=\"\", pod=~\"ama-metrics.*\"}) - sum ( node_namespace_pod_container:container_cpu_usage_seconds_total:sum_irate{cluster=\"ci-prod-aks-mac-weu\", namespace=\"kube-system\", pod=~\"ama-metrics-node.*\"}) - sum ( node_namespace_pod_container:container_cpu_usage_seconds_total:sum_irate{cluster=\"ci-prod-aks-mac-weu\", namespace=\"kube-system\", pod=~\"ama-metrics-ksm.*\"}))/ sum(kube_pod_container_resource_limits{job=\"kube-state-metrics\", cluster=\"ci-prod-aks-mac-weu\", namespace=\"kube-system\", resource=\"cpu\"})",
            "refId": "A"
          }
        ],
        "title": "Replicaset CPU %",
        "type": "timeseries"
      },
      {
        "datasource": {
          "type": "prometheus",
          "uid": "ci-prod-aks-weu-mac"
        },
        "fieldConfig": {
          "defaults": {
            "color": {
              "mode": "palette-classic"
            },
            "custom": {
              "axisLabel": "",
              "axisPlacement": "auto",
              "barAlignment": 0,
              "drawStyle": "line",
              "fillOpacity": 0,
              "gradientMode": "none",
              "hideFrom": {
                "legend": false,
                "tooltip": false,
                "viz": false
              },
              "lineInterpolation": "linear",
              "lineWidth": 1,
              "pointSize": 5,
              "scaleDistribution": {
                "type": "linear"
              },
              "showPoints": "auto",
              "spanNulls": false,
              "stacking": {
                "group": "A",
                "mode": "none"
              },
              "thresholdsStyle": {
                "mode": "off"
              }
            },
            "mappings": [],
            "thresholds": {
              "mode": "absolute",
              "steps": [
                {
                  "color": "green",
                  "value": null
                },
                {
                  "color": "red",
                  "value": 80
                }
              ]
            }
          },
          "overrides": []
        },
        "gridPos": {
          "h": 8,
          "w": 12,
          "x": 12,
          "y": 0
        },
        "id": 8,
        "options": {
          "legend": {
            "calcs": [],
            "displayMode": "list",
            "placement": "bottom"
          },
          "tooltip": {
            "mode": "single",
            "sort": "none"
          }
        },
        "targets": [
          {
            "datasource": {
              "type": "prometheus",
              "uid": "ci-prod-aks-weu-mac"
            },
            "expr": "sum(container_memory_working_set_bytes{job=\"cadvisor\", cluster=\"ci-prod-aks-mac-weu\", namespace=\"kube-system\",container!=\"\", image!=\"\", pod=~\"ama-metrics-ksm.*\"}) / sum(kube_pod_container_resource_limits{job=\"kube-state-metrics\", cluster=\"ci-prod-aks-mac-weu\", namespace=\"kube-system\", resource=\"memory\"})",
            "refId": "A"
          }
        ],
        "title": "K-S-M Memory%",
        "type": "timeseries"
      },
      {
        "datasource": {
          "type": "prometheus",
          "uid": "ci-prod-aks-weu-mac"
        },
        "fieldConfig": {
          "defaults": {
            "color": {
              "mode": "palette-classic"
            },
            "custom": {
              "axisLabel": "",
              "axisPlacement": "auto",
              "barAlignment": 0,
              "drawStyle": "line",
              "fillOpacity": 0,
              "gradientMode": "none",
              "hideFrom": {
                "legend": false,
                "tooltip": false,
                "viz": false
              },
              "lineInterpolation": "linear",
              "lineWidth": 1,
              "pointSize": 5,
              "scaleDistribution": {
                "type": "linear"
              },
              "showPoints": "auto",
              "spanNulls": false,
              "stacking": {
                "group": "A",
                "mode": "none"
              },
              "thresholdsStyle": {
                "mode": "off"
              }
            },
            "mappings": [],
            "thresholds": {
              "mode": "absolute",
              "steps": [
                {
                  "color": "green",
                  "value": null
                },
                {
                  "color": "red",
                  "value": 80
                }
              ]
            }
          },
          "overrides": []
        },
        "gridPos": {
          "h": 8,
          "w": 12,
          "x": 0,
          "y": 8
        },
        "id": 4,
        "options": {
          "legend": {
            "calcs": [],
            "displayMode": "list",
            "placement": "bottom"
          },
          "tooltip": {
            "mode": "single",
            "sort": "none"
          }
        },
        "targets": [
          {
            "datasource": {
              "type": "prometheus",
              "uid": "ci-prod-aks-weu-mac"
            },
            "expr": "sum ( node_namespace_pod_container:container_cpu_usage_seconds_total:sum_irate{cluster=\"ci-prod-aks-mac-weu\", namespace=\"kube-system\", container!=\"\", pod=~\"ama-metrics-node.*\"})  / sum(kube_pod_container_resource_limits{job=\"kube-state-metrics\", cluster=\"ci-prod-aks-mac-weu\", namespace=\"kube-system\", resource=\"cpu\"}) ",
            "refId": "A"
          }
        ],
        "title": "Daemonset CPU%",
        "type": "timeseries"
      },
      {
        "datasource": {
          "type": "prometheus",
          "uid": "ci-prod-aks-weu-mac"
        },
        "fieldConfig": {
          "defaults": {
            "color": {
              "mode": "palette-classic"
            },
            "custom": {
              "axisLabel": "",
              "axisPlacement": "auto",
              "barAlignment": 0,
              "drawStyle": "line",
              "fillOpacity": 0,
              "gradientMode": "none",
              "hideFrom": {
                "legend": false,
                "tooltip": false,
                "viz": false
              },
              "lineInterpolation": "linear",
              "lineWidth": 1,
              "pointSize": 5,
              "scaleDistribution": {
                "type": "linear"
              },
              "showPoints": "auto",
              "spanNulls": false,
              "stacking": {
                "group": "A",
                "mode": "none"
              },
              "thresholdsStyle": {
                "mode": "off"
              }
            },
            "mappings": [],
            "thresholds": {
              "mode": "absolute",
              "steps": [
                {
                  "color": "green",
                  "value": null
                },
                {
                  "color": "red",
                  "value": 80
                }
              ]
            }
          },
          "overrides": []
        },
        "gridPos": {
          "h": 8,
          "w": 12,
          "x": 12,
          "y": 8
        },
        "id": 10,
        "options": {
          "legend": {
            "calcs": [],
            "displayMode": "list",
            "placement": "bottom"
          },
          "tooltip": {
            "mode": "single",
            "sort": "none"
          }
        },
        "targets": [
          {
            "datasource": {
              "type": "prometheus",
              "uid": "ci-prod-aks-weu-mac"
            },
            "expr": "sum(container_memory_working_set_bytes{job=\"cadvisor\", cluster=\"ci-prod-aks-mac-weu\", namespace=\"kube-system\",container!=\"\", image!=\"\", pod=~\"ama-metrics-node.*\"}) / sum(kube_pod_container_resource_limits{job=\"kube-state-metrics\", cluster=\"ci-prod-aks-mac-weu\", namespace=\"kube-system\", resource=\"memory\"})",
            "refId": "A"
          }
        ],
        "title": "Daemonset Memory%",
        "type": "timeseries"
      },
      {
        "datasource": {
          "type": "prometheus",
          "uid": "ci-prod-aks-weu-mac"
        },
        "fieldConfig": {
          "defaults": {
            "color": {
              "mode": "palette-classic"
            },
            "custom": {
              "axisLabel": "",
              "axisPlacement": "auto",
              "barAlignment": 0,
              "drawStyle": "line",
              "fillOpacity": 0,
              "gradientMode": "none",
              "hideFrom": {
                "legend": false,
                "tooltip": false,
                "viz": false
              },
              "lineInterpolation": "linear",
              "lineWidth": 1,
              "pointSize": 5,
              "scaleDistribution": {
                "type": "linear"
              },
              "showPoints": "auto",
              "spanNulls": false,
              "stacking": {
                "group": "A",
                "mode": "none"
              },
              "thresholdsStyle": {
                "mode": "off"
              }
            },
            "mappings": [],
            "thresholds": {
              "mode": "absolute",
              "steps": [
                {
                  "color": "green",
                  "value": null
                },
                {
                  "color": "red",
                  "value": 80
                }
              ]
            }
          },
          "overrides": []
        },
        "gridPos": {
          "h": 9,
          "w": 12,
          "x": 0,
          "y": 16
        },
        "id": 2,
        "options": {
          "legend": {
            "calcs": [],
            "displayMode": "list",
            "placement": "bottom"
          },
          "tooltip": {
            "mode": "single",
            "sort": "none"
          }
        },
        "targets": [
          {
            "datasource": {
              "type": "prometheus",
              "uid": "ci-prod-aks-weu-mac"
            },
            "editorMode": "code",
            "expr": "sum ( node_namespace_pod_container:container_cpu_usage_seconds_total:sum_irate{cluster=\"ci-prod-aks-mac-weu\", namespace=\"kube-system\", container!=\"\", pod=~\"ama-metrics-ksm.*\"})/ sum(kube_pod_container_resource_limits{job=\"kube-state-metrics\", cluster=\"ci-prod-aks-mac-weu\", namespace=\"kube-system\", resource=\"cpu\"})",
            "legendFormat": "__auto",
            "range": true,
            "refId": "A"
          }
        ],
        "title": "K-S-M CPU%",
        "type": "timeseries"
      },
      {
        "datasource": {
          "type": "prometheus",
          "uid": "ci-prod-aks-weu-mac"
        },
        "fieldConfig": {
          "defaults": {
            "color": {
              "mode": "palette-classic"
            },
            "custom": {
              "axisLabel": "",
              "axisPlacement": "auto",
              "barAlignment": 0,
              "drawStyle": "line",
              "fillOpacity": 0,
              "gradientMode": "none",
              "hideFrom": {
                "legend": false,
                "tooltip": false,
                "viz": false
              },
              "lineInterpolation": "linear",
              "lineWidth": 1,
              "pointSize": 5,
              "scaleDistribution": {
                "type": "linear"
              },
              "showPoints": "auto",
              "spanNulls": false,
              "stacking": {
                "group": "A",
                "mode": "none"
              },
              "thresholdsStyle": {
                "mode": "off"
              }
            },
            "mappings": [],
            "thresholds": {
              "mode": "absolute",
              "steps": [
                {
                  "color": "green",
                  "value": null
                },
                {
                  "color": "red",
                  "value": 80
                }
              ]
            }
          },
          "overrides": []
        },
        "gridPos": {
          "h": 8,
          "w": 12,
          "x": 12,
          "y": 16
        },
        "id": 12,
        "options": {
          "legend": {
            "calcs": [],
            "displayMode": "list",
            "placement": "bottom"
          },
          "tooltip": {
            "mode": "single",
            "sort": "none"
          }
        },
        "targets": [
          {
            "datasource": {
              "type": "prometheus",
              "uid": "ci-prod-aks-weu-mac"
            },
            "expr": "(sum(container_memory_working_set_bytes{job=\"cadvisor\", cluster=\"ci-prod-aks-mac-weu\", namespace=\"kube-system\",container!=\"\", image!=\"\", pod=~\"ama-metrics.*\"}) - sum(container_memory_working_set_bytes{job=\"cadvisor\", cluster=\"ci-prod-aks-mac-weu\", namespace=\"kube-system\",container!=\"\", image!=\"\", pod=~\"ama-metrics-node.*\"}) - sum(container_memory_working_set_bytes{job=\"cadvisor\", cluster=\"ci-prod-aks-mac-weu\", namespace=\"kube-system\",container!=\"\", image!=\"\", pod=~\"ama-metrics-ksm.*\"})) / sum(kube_pod_container_resource_limits{job=\"kube-state-metrics\", cluster=\"ci-prod-aks-mac-weu\", namespace=\"kube-system\", resource=\"memory\"})",
            "refId": "A"
          }
        ],
        "title": "Replicaset Memory%",
        "type": "timeseries"
      }
    ],
    "schemaVersion": 36,
    "style": "dark",
    "tags": [],
    "templating": {
      "list": []
    },
    "time": {
      "from": "now-6h",
      "to": "now"
    },
    "timepicker": {},
    "timezone": "",
    "title": "CPU and Memory utilization k-s-m, replicaset and daemonset",
    "uid": "gp9556IVz",
    "version": 3,
    "weekStart": ""
  }